asynczipstream/__init__.py
asynczipstream/compat.py
asynczipstream-1.0.1.dist-info/LICENSE
asynczipstream-1.0.1.dist-info/METADATA
asynczipstream-1.0.1.dist-info/WHEEL
asynczipstream-1.0.1.dist-info/top_level.txt
asynczipstream-1.0.1.dist-info/RECORD
