Metadata-Version: 2.1
Name: asynczipstream
Version: 1.0.1
Summary: Asynchronous Zipfile generator that takes input files as well as streams
Home-page: https://github.com/lososkin/python-zipstream-aio
Author: lososkin
Author-email: yalososka@gmail.com
Keywords: async zip streaming
Classifier: Programming Language :: Python
Classifier: License :: OSI Approved :: GNU General Public License v3 (GPLv3)
Classifier: Operating System :: OS Independent
Classifier: Topic :: System :: Archiving :: Compression
License-File: LICENSE
Requires-Dist: aiofiles (>22.1.0)
